{
"time": "6/14/2012 9:13:43 AM",
"avgcovariancedeterminant": "413603487345.08",
"ins": {"x": 21090.00, "y": -20870.00, "z": 1420.00, "yaw": 1.57, "roll": 0.00, "pitch": 0.00 },
"slam": {"x": 21100.04, "y": -20857.79, "yaw": 1.57 },
"groundtruth": {"x": 21080.00, "y": -20850.00, "z": 1720.00, "yaw": 1.57, "pitch": 0.00, "roll": 0.00 }
},
{
"time": "6/14/2012 9:13:43 AM",
"avgcovariancedeterminant": "386487320851.808",
"ins": {"x": 21100.00, "y": -20210.00, "z": 1400.00, "yaw": 1.60, "roll": 6.28, "pitch": 0.01 },
"slam": {"x": 21089.90, "y": -20217.13, "yaw": 1.60 },
"groundtruth": {"x": 21060.00, "y": -20150.00, "z": 1720.00, "yaw": 1.60, "pitch": 0.01, "roll": 0.00 }
},
{
"time": "6/14/2012 9:13:43 AM",
"avgcovariancedeterminant": "360731611823.199",
"ins": {"x": 21070.00, "y": -19450.00, "z": 1380.00, "yaw": 1.60, "roll": 6.28, "pitch": 0.02 },
"slam": {"x": 21078.19, "y": -19453.72, "yaw": 1.60 },
"groundtruth": {"x": 21040.00, "y": -19440.00, "z": 1710.00, "yaw": 1.60, "pitch": 0.02, "roll": 0.00 }
},
{
"time": "6/14/2012 9:13:43 AM",
"avgcovariancedeterminant": "336757155070.594",
"ins": {"x": 21060.00, "y": -18860.00, "z": 1390.00, "yaw": 1.61, "roll": 0.00, "pitch": 0.02 },
"slam": {"x": 21053.31, "y": -18859.93, "yaw": 1.62 },
"groundtruth": {"x": 21010.00, "y": -18740.00, "z": 1720.00, "yaw": 1.62, "pitch": 0.01, "roll": 0.00 }
},
{
"time": "6/14/2012 9:13:43 AM",
"avgcovariancedeterminant": "325930187705.802",
"ins": {"x": 21070.00, "y": -18440.00, "z": 1400.00, "yaw": 1.56, "roll": 0.00, "pitch": 0.00 },
"slam": {"x": 21037.56, "y": -18436.82, "yaw": 1.57 },
"groundtruth": {"x": 20990.00, "y": -18420.00, "z": 1720.00, "yaw": 1.57, "pitch": 0.00, "roll": 0.00 }
},
{
"time": "6/14/2012 9:13:44 AM",
"avgcovariancedeterminant": "488193282719.657",
"ins": {"x": 21060.00, "y": -18470.00, "z": 1390.00, "yaw": 1.18, "roll": 6.28, "pitch": 0.00 },
"slam": {"x": 20988.58, "y": -18469.87, "yaw": 1.18 },
"groundtruth": {"x": 20970.00, "y": -18460.00, "z": 1720.00, "yaw": 1.18, "pitch": 0.00, "roll": 0.00 }
},
{
"time": "6/14/2012 9:13:44 AM",
"avgcovariancedeterminant": "316300710766.448",
"ins": {"x": 21220.00, "y": -18030.00, "z": 1420.00, "yaw": 1.19, "roll": 6.28, "pitch": 0.02 },
"slam": {"x": 21201.07, "y": -18017.78, "yaw": 1.18 },
"groundtruth": {"x": 21180.00, "y": -17930.00, "z": 1720.00, "yaw": 1.19, "pitch": 0.00, "roll": 0.00 }
},
{
"time": "6/14/2012 9:13:44 AM",
"avgcovariancedeterminant": "306844513317.431",
"ins": {"x": 21520.00, "y": -17290.00, "z": 1450.00, "yaw": 1.18, "roll": 6.28, "pitch": 0.01 },
"slam": {"x": 21475.92, "y": -17300.27, "yaw": 1.18 },
"groundtruth": {"x": 21450.00, "y": -17270.00, "z": 1720.00, "yaw": 1.18, "pitch": 0.01, "roll": 0.00 }
},
{
"time": "6/14/2012 9:13:44 AM",
"avgcovariancedeterminant": "304605845050.424",
"ins": {"x": 21610.00, "y": -17020.00, "z": 1440.00, "yaw": 1.47, "roll": 6.28, "pitch": 0.00 },
"slam": {"x": 21618.79, "y": -17017.11, "yaw": 1.52 },
"groundtruth": {"x": 21560.00, "y": -17010.00, "z": 1720.00, "yaw": 1.53, "pitch": 0.00, "roll": 0.00 }
},
{
"time": "6/14/2012 9:13:44 AM",
"avgcovariancedeterminant": "305052007306.44",
"ins": {"x": 21610.00, "y": -17020.00, "z": 1440.00, "yaw": 1.72, "roll": 0.00, "pitch": 0.00 },
"slam": {"x": 21634.05, "y": -17000.39, "yaw": 1.72 },
"groundtruth": {"x": 21560.00, "y": -17010.00, "z": 1720.00, "yaw": 1.72, "pitch": 0.00, "roll": 0.00 }
},
{
"time": "6/14/2012 9:13:44 AM",
"avgcovariancedeterminant": "285197819203.38",
"ins": {"x": 21560.00, "y": -16390.00, "z": 1430.00, "yaw": 1.70, "roll": 6.28, "pitch": 0.05 },
"slam": {"x": 21565.30, "y": -16393.78, "yaw": 1.70 },
"groundtruth": {"x": 21480.00, "y": -16350.00, "z": 1710.00, "yaw": 1.70, "pitch": 0.04, "roll": 0.00 }
},
{
"time": "6/14/2012 9:13:44 AM",
"avgcovariancedeterminant": "267925014962.773",
"ins": {"x": 21490.00, "y": -15790.00, "z": 1420.00, "yaw": 1.70, "roll": 0.00, "pitch": 0.01 },
"slam": {"x": 21499.37, "y": -15792.30, "yaw": 1.69 },
"groundtruth": {"x": 21410.00, "y": -15770.00, "z": 1720.00, "yaw": 1.69, "pitch": 0.00, "roll": 0.00 }
},
{
"time": "6/14/2012 9:13:45 AM",
"avgcovariancedeterminant": "267932874876.437",
"ins": {"x": 21490.00, "y": -15800.00, "z": 1420.00, "yaw": 1.47, "roll": 0.00, "pitch": 0.00 },
"slam": {"x": 21479.18, "y": -15783.04, "yaw": 1.48 },
"groundtruth": {"x": 21400.00, "y": -15780.00, "z": 1720.00, "yaw": 1.48, "pitch": 0.00, "roll": 0.00 }
},
{
"time": "6/14/2012 9:13:45 AM",
"avgcovariancedeterminant": "266741700173.269",
"ins": {"x": 21500.00, "y": -15780.00, "z": 1420.00, "yaw": 1.21, "roll": 0.00, "pitch": 0.00 },
"slam": {"x": 21470.96, "y": -15766.29, "yaw": 1.18 },
"groundtruth": {"x": 21420.00, "y": -15750.00, "z": 1720.00, "yaw": 1.18, "pitch": 0.00, "roll": 0.00 }
},
{
"time": "6/14/2012 9:13:45 AM",
"avgcovariancedeterminant": "264786053409.142",
"ins": {"x": 21700.00, "y": -15440.00, "z": 1420.00, "yaw": 1.01, "roll": 0.00, "pitch": 0.01 },
"slam": {"x": 21666.18, "y": -15426.75, "yaw": 1.02 },
"groundtruth": {"x": 21620.00, "y": -15410.00, "z": 1720.00, "yaw": 1.02, "pitch": 0.00, "roll": 0.00 }
},
{
"time": "6/14/2012 9:13:45 AM",
"avgcovariancedeterminant": "526192840556.684",
"ins": {"x": 22050.00, "y": -14890.00, "z": 1430.00, "yaw": 1.01, "roll": 0.00, "pitch": 0.01 },
"slam": {"x": 22049.80, "y": -14887.31, "yaw": 1.02 },
"groundtruth": {"x": 22000.00, "y": -14800.00, "z": 1720.00, "yaw": 1.02, "pitch": 0.00, "roll": 0.00 }
},
{
"time": "6/14/2012 9:13:45 AM",
"avgcovariancedeterminant": "262355775789.215",
"ins": {"x": 22500.00, "y": -14190.00, "z": 1420.00, "yaw": 1.01, "roll": 0.00, "pitch": 0.01 },
"slam": {"x": 22440.27, "y": -14188.03, "yaw": 1.01 },
"groundtruth": {"x": 22380.00, "y": -14180.00, "z": 1720.00, "yaw": 1.02, "pitch": 0.00, "roll": 0.00 }
},
{
"time": "6/14/2012 9:13:45 AM",
"avgcovariancedeterminant": "261953519740.479",
"ins": {"x": 22660.00, "y": -13890.00, "z": 1430.00, "yaw": 1.01, "roll": 0.00, "pitch": 0.01 },
"slam": {"x": 22619.04, "y": -13895.10, "yaw": 1.01 },
"groundtruth": {"x": 22550.00, "y": -13890.00, "z": 1720.00, "yaw": 1.02, "pitch": 0.00, "roll": 0.00 }
},
{
"time": "6/14/2012 9:13:45 AM",
"avgcovariancedeterminant": "261951827570.22",
"ins": {"x": 22660.00, "y": -13890.00, "z": 1430.00, "yaw": 1.10, "roll": 0.00, "pitch": 0.01 },
"slam": {"x": 22619.16, "y": -13894.48, "yaw": 1.10 },
"groundtruth": {"x": 22550.00, "y": -13900.00, "z": 1720.00, "yaw": 1.11, "pitch": 0.00, "roll": 0.00 }
},
{
"time": "6/14/2012 9:13:45 AM",
"avgcovariancedeterminant": "263930178331.948",
"ins": {"x": 22650.00, "y": -13940.00, "z": 1430.00, "yaw": 1.38, "roll": 0.00, "pitch": 0.00 },
"slam": {"x": 22627.42, "y": -13934.88, "yaw": 1.39 },
"groundtruth": {"x": 22530.00, "y": -13960.00, "z": 1720.00, "yaw": 1.39, "pitch": 0.00, "roll": 0.00 }
},
{
"time": "6/14/2012 9:13:46 AM",
"avgcovariancedeterminant": "256853583916.18",
"ins": {"x": 22730.00, "y": -13520.00, "z": 1440.00, "yaw": 1.36, "roll": 6.28, "pitch": 0.01 },
"slam": {"x": 22735.97, "y": -13520.43, "yaw": 1.37 },
"groundtruth": {"x": 22640.00, "y": -13450.00, "z": 1720.00, "yaw": 1.37, "pitch": 0.01, "roll": 0.00 }
},
{
"time": "6/14/2012 9:13:46 AM",
"avgcovariancedeterminant": "248022737352.558",
"ins": {"x": 22870.00, "y": -12740.00, "z": 1430.00, "yaw": 1.35, "roll": 0.00, "pitch": 0.04 },
"slam": {"x": 22892.14, "y": -12731.84, "yaw": 1.36 },
"groundtruth": {"x": 22780.00, "y": -12750.00, "z": 1710.00, "yaw": 1.36, "pitch": 0.03, "roll": 0.00 }
},
{
"time": "6/14/2012 9:14:20 AM",
"avgcovariancedeterminant": "866919066545.39",
"ins": {"x": 21060.00, "y": -21390.00, "z": 1430.00, "yaw": 1.57, "roll": 0.00, "pitch": 0.00 },
"slam": {"x": 21083.15, "y": -21367.46, "yaw": 1.57 },
"groundtruth": {"x": 21080.00, "y": -21340.00, "z": 1710.00, "yaw": 1.57, "pitch": 0.03, "roll": 0.00 }
},
{
"time": "6/14/2012 9:14:21 AM",
"avgcovariancedeterminant": "411943888305.897",
"ins": {"x": 21100.00, "y": -20820.00, "z": 1440.00, "yaw": 1.42, "roll": 6.28, "pitch": 6.28 },
"slam": {"x": 21083.55, "y": -20817.70, "yaw": 1.42 },
"groundtruth": {"x": 21090.00, "y": -20820.00, "z": 1720.00, "yaw": 1.42, "pitch": 0.00, "roll": 0.00 }
},
{
"time": "6/14/2012 9:14:21 AM",
"avgcovariancedeterminant": "412513395853.067",
"ins": {"x": 21100.00, "y": -20850.00, "z": 1440.00, "yaw": 1.26, "roll": 6.28, "pitch": 6.28 },
"slam": {"x": 21066.19, "y": -20851.00, "yaw": 1.26 },
"groundtruth": {"x": 21080.00, "y": -20840.00, "z": 1720.00, "yaw": 1.27, "pitch": 0.00, "roll": 0.00 }
},
{
"time": "6/14/2012 9:14:22 AM",
"avgcovariancedeterminant": "404813462281.291",
"ins": {"x": 21180.00, "y": -20560.00, "z": 1440.00, "yaw": 1.28, "roll": 0.00, "pitch": 0.01 },
"slam": {"x": 21148.45, "y": -20553.73, "yaw": 1.28 },
"groundtruth": {"x": 21160.00, "y": -20570.00, "z": 1720.00, "yaw": 1.28, "pitch": 0.01, "roll": 0.00 }
},
{
"time": "6/14/2012 9:14:22 AM",
"avgcovariancedeterminant": "393423151680.544",
"ins": {"x": 21320.00, "y": -20110.00, "z": 1450.00, "yaw": 1.27, "roll": 0.00, "pitch": 0.01 },
"slam": {"x": 21286.69, "y": -20105.28, "yaw": 1.27 },
"groundtruth": {"x": 21290.00, "y": -20120.00, "z": 1720.00, "yaw": 1.27, "pitch": 0.01, "roll": 0.00 }
},
{
"time": "6/14/2012 9:14:23 AM",
"avgcovariancedeterminant": "382286794108.574",
"ins": {"x": 21450.00, "y": -19670.00, "z": 1450.00, "yaw": 1.29, "roll": 6.28, "pitch": 0.02 },
"slam": {"x": 21425.78, "y": -19666.88, "yaw": 1.29 },
"groundtruth": {"x": 21430.00, "y": -19660.00, "z": 1710.00, "yaw": 1.29, "pitch": 0.02, "roll": 0.00 }
},
{
"time": "6/14/2012 9:14:24 AM",
"avgcovariancedeterminant": "371936080001.519",
"ins": {"x": 21600.00, "y": -19210.00, "z": 1500.00, "yaw": 1.27, "roll": 0.00, "pitch": 0.00 },
"slam": {"x": 21573.00, "y": -19205.18, "yaw": 1.27 },
"groundtruth": {"x": 21570.00, "y": -19210.00, "z": 1720.00, "yaw": 1.27, "pitch": 0.00, "roll": 0.00 }
},
{
"time": "6/14/2012 9:14:24 AM",
"avgcovariancedeterminant": "366280237266.547",
"ins": {"x": 21630.00, "y": -19030.00, "z": 1510.00, "yaw": 1.29, "roll": 6.28, "pitch": 0.01 },
"slam": {"x": 21641.40, "y": -19011.14, "yaw": 1.28 },
"groundtruth": {"x": 21640.00, "y": -18980.00, "z": 1720.00, "yaw": 1.28, "pitch": 0.00, "roll": 0.00 }
},
{
"time": "6/14/2012 9:14:24 AM",
"avgcovariancedeterminant": "723367316085.546",
"ins": {"x": 21720.00, "y": -18730.00, "z": 1480.00, "yaw": 1.26, "roll": 0.00, "pitch": 0.01 },
"slam": {"x": 21716.29, "y": -18735.17, "yaw": 1.26 },
"groundtruth": {"x": 21710.00, "y": -18760.00, "z": 1720.00, "yaw": 1.26, "pitch": 0.01, "roll": 0.00 }
},
{
"time": "6/14/2012 9:14:25 AM",
"avgcovariancedeterminant": "704433472527.952",
"ins": {"x": 21830.00, "y": -18280.00, "z": 1500.00, "yaw": 1.28, "roll": 0.00, "pitch": 0.01 },
"slam": {"x": 21857.56, "y": -18312.67, "yaw": 1.27 },
"groundtruth": {"x": 21840.00, "y": -18310.00, "z": 1720.00, "yaw": 1.27, "pitch": 0.01, "roll": 0.00 }
},
{
"time": "6/14/2012 9:14:25 AM",
"avgcovariancedeterminant": "343472825113.507",
"ins": {"x": 21960.00, "y": -17820.00, "z": 1480.00, "yaw": 1.27, "roll": 0.00, "pitch": 0.00 },
"slam": {"x": 22008.02, "y": -17824.47, "yaw": 1.27 },
"groundtruth": {"x": 21990.00, "y": -17850.00, "z": 1720.00, "yaw": 1.27, "pitch": 0.00, "roll": 0.00 }
},
{
"time": "6/14/2012 9:14:26 AM",
"avgcovariancedeterminant": "335318483751.442",
"ins": {"x": 22090.00, "y": -17380.00, "z": 1480.00, "yaw": 1.26, "roll": 0.00, "pitch": 0.02 },
"slam": {"x": 22155.70, "y": -17376.81, "yaw": 1.26 },
"groundtruth": {"x": 22130.00, "y": -17400.00, "z": 1720.00, "yaw": 1.26, "pitch": 0.02, "roll": 0.00 }
},
{
"time": "6/14/2012 9:14:27 AM",
"avgcovariancedeterminant": "327319781671.678",
"ins": {"x": 22230.00, "y": -16920.00, "z": 1480.00, "yaw": 1.28, "roll": 0.00, "pitch": 0.01 },
"slam": {"x": 22303.60, "y": -16910.58, "yaw": 1.27 },
"groundtruth": {"x": 22270.00, "y": -16940.00, "z": 1720.00, "yaw": 1.28, "pitch": 0.01, "roll": 0.00 }
},
{
"time": "6/14/2012 9:14:27 AM",
"avgcovariancedeterminant": "639745143245.108",
"ins": {"x": 22380.00, "y": -16480.00, "z": 1490.00, "yaw": 1.27, "roll": 0.00, "pitch": 0.01 },
"slam": {"x": 22445.98, "y": -16491.04, "yaw": 1.27 },
"groundtruth": {"x": 22410.00, "y": -16500.00, "z": 1720.00, "yaw": 1.27, "pitch": 0.01, "roll": 0.00 }
},
{
"time": "6/14/2012 9:14:27 AM",
"avgcovariancedeterminant": "316267958741.23",
"ins": {"x": 22430.00, "y": -16300.00, "z": 1480.00, "yaw": 1.29, "roll": 6.28, "pitch": 0.01 },
"slam": {"x": 22515.09, "y": -16302.68, "yaw": 1.28 },
"groundtruth": {"x": 22470.00, "y": -16260.00, "z": 1710.00, "yaw": 1.29, "pitch": 0.03, "roll": 0.00 }
},
{
"time": "6/14/2012 9:14:27 AM",
"avgcovariancedeterminant": "313090393041.603",
"ins": {"x": 22520.00, "y": -16000.00, "z": 1480.00, "yaw": 1.25, "roll": 6.28, "pitch": 0.01 },
"slam": {"x": 22594.02, "y": -15998.09, "yaw": 1.25 },
"groundtruth": {"x": 22550.00, "y": -16050.00, "z": 1720.00, "yaw": 1.25, "pitch": 0.01, "roll": 0.00 }
},
{
"time": "6/14/2012 9:14:29 AM",
"avgcovariancedeterminant": "301085817226.109",
"ins": {"x": 22780.00, "y": -15090.00, "z": 1500.00, "yaw": 1.25, "roll": 0.00, "pitch": 0.01 },
"slam": {"x": 22900.18, "y": -15093.59, "yaw": 1.25 },
"groundtruth": {"x": 22840.00, "y": -15150.00, "z": 1720.00, "yaw": 1.25, "pitch": 0.01, "roll": 0.00 }
},
{
"time": "6/14/2012 9:14:31 AM",
"avgcovariancedeterminant": "300209895508.283",
"ins": {"x": 22810.00, "y": -14970.00, "z": 1490.00, "yaw": 1.46, "roll": 0.00, "pitch": 0.00 },
"slam": {"x": 22956.70, "y": -14970.49, "yaw": 1.47 },
"groundtruth": {"x": 22880.00, "y": -15020.00, "z": 1720.00, "yaw": 1.47, "pitch": 0.00, "roll": 0.00 }
},
{
"time": "6/14/2012 9:14:31 AM",
"avgcovariancedeterminant": "300653933467.784",
"ins": {"x": 22820.00, "y": -14950.00, "z": 1490.00, "yaw": 1.56, "roll": 0.00, "pitch": 0.00 },
"slam": {"x": 22980.77, "y": -14953.90, "yaw": 1.60 },
"groundtruth": {"x": 22890.00, "y": -15010.00, "z": 1720.00, "yaw": 1.61, "pitch": 0.00, "roll": 0.00 }
},
{
"time": "6/14/2012 9:14:32 AM",
"avgcovariancedeterminant": "289007755007.31",
"ins": {"x": 22790.00, "y": -14510.00, "z": 1460.00, "yaw": 1.64, "roll": 0.00, "pitch": 0.01 },
"slam": {"x": 22958.47, "y": -14500.85, "yaw": 1.65 },
"groundtruth": {"x": 22860.00, "y": -14560.00, "z": 1720.00, "yaw": 1.65, "pitch": 0.01, "roll": 0.00 }
},
{
"time": "6/14/2012 9:14:33 AM",
"avgcovariancedeterminant": "416495260807.558",
"ins": {"x": 22740.00, "y": -14050.00, "z": 1470.00, "yaw": 1.63, "roll": 0.00, "pitch": 0.01 },
"slam": {"x": 22930.47, "y": -14047.06, "yaw": 1.64 },
"groundtruth": {"x": 22830.00, "y": -14100.00, "z": 1720.00, "yaw": 1.64, "pitch": 0.01, "roll": 0.00 }
},
{
"time": "6/14/2012 9:14:33 AM",
"avgcovariancedeterminant": "533354469662.941",
"ins": {"x": 22690.00, "y": -13560.00, "z": 1460.00, "yaw": 1.62, "roll": 6.28, "pitch": 0.01 },
"slam": {"x": 22906.67, "y": -13583.25, "yaw": 1.62 },
"groundtruth": {"x": 22800.00, "y": -13630.00, "z": 1720.00, "yaw": 1.63, "pitch": 0.00, "roll": 0.00 }
},
{
"time": "6/14/2012 9:14:33 AM",
"avgcovariancedeterminant": "256087954171.758",
"ins": {"x": 22680.00, "y": -13080.00, "z": 1460.00, "yaw": 1.60, "roll": 0.00, "pitch": 0.01 },
"slam": {"x": 22891.48, "y": -13077.94, "yaw": 1.61 },
"groundtruth": {"x": 22770.00, "y": -13150.00, "z": 1720.00, "yaw": 1.61, "pitch": 0.01, "roll": 0.00 }
},
{
"time": "6/14/2012 9:14:35 AM",
"avgcovariancedeterminant": "246898571088.016",
"ins": {"x": 22680.00, "y": -12610.00, "z": 1470.00, "yaw": 1.61, "roll": 0.00, "pitch": 0.03 },
"slam": {"x": 22878.67, "y": -12606.40, "yaw": 1.62 },
"groundtruth": {"x": 22750.00, "y": -12690.00, "z": 1710.00, "yaw": 1.62, "pitch": 0.02, "roll": 0.00 }
},
{
"time": "6/14/2012 9:14:35 AM",
"avgcovariancedeterminant": "237590537465.098",
"ins": {"x": 22670.00, "y": -12120.00, "z": 1470.00, "yaw": 1.61, "roll": 0.01, "pitch": 0.01 },
"slam": {"x": 22865.37, "y": -12114.27, "yaw": 1.62 },
"groundtruth": {"x": 22730.00, "y": -12200.00, "z": 1720.00, "yaw": 1.62, "pitch": 0.01, "roll": 0.00 }
},
{
"time": "6/14/2012 9:14:35 AM",
"avgcovariancedeterminant": "229259412719.42",
"ins": {"x": 22660.00, "y": -11670.00, "z": 1470.00, "yaw": 1.59, "roll": 0.00, "pitch": 0.00 },
"slam": {"x": 22855.06, "y": -11658.18, "yaw": 1.60 },
"groundtruth": {"x": 22720.00, "y": -11740.00, "z": 1720.00, "yaw": 1.60, "pitch": 0.00, "roll": 0.00 }
},
{
"time": "6/14/2012 9:14:36 AM",
"avgcovariancedeterminant": "221152668077.138",
"ins": {"x": 22630.00, "y": -11220.00, "z": 1480.00, "yaw": 1.61, "roll": 0.00, "pitch": 0.03 },
"slam": {"x": 22841.89, "y": -11221.04, "yaw": 1.61 },
"groundtruth": {"x": 22700.00, "y": -11290.00, "z": 1710.00, "yaw": 1.62, "pitch": 0.03, "roll": 0.00 }
},
{
"time": "6/14/2012 9:14:37 AM",
"avgcovariancedeterminant": "213270702284.031",
"ins": {"x": 22600.00, "y": -10750.00, "z": 1490.00, "yaw": 1.60, "roll": 6.28, "pitch": 0.02 },
"slam": {"x": 22828.43, "y": -10746.90, "yaw": 1.61 },
"groundtruth": {"x": 22680.00, "y": -10800.00, "z": 1710.00, "yaw": 1.61, "pitch": 0.02, "roll": 0.00 }
},
{
"time": "6/14/2012 9:14:37 AM",
"avgcovariancedeterminant": "206254637454.062",
"ins": {"x": 22600.00, "y": -10310.00, "z": 1480.00, "yaw": 1.59, "roll": 0.00, "pitch": 0.01 },
"slam": {"x": 22818.85, "y": -10306.54, "yaw": 1.60 },
"groundtruth": {"x": 22660.00, "y": -10340.00, "z": 1720.00, "yaw": 1.60, "pitch": 0.01, "roll": 0.00 }
},
{
"time": "6/14/2012 9:14:38 AM",
"avgcovariancedeterminant": "199720663102.726",
"ins": {"x": 22570.00, "y": -9830.00, "z": 1480.00, "yaw": 1.60, "roll": 6.28, "pitch": 0.00 },
"slam": {"x": 22809.64, "y": -9829.39, "yaw": 1.61 },
"groundtruth": {"x": 22650.00, "y": -9870.00, "z": 1720.00, "yaw": 1.61, "pitch": 0.00, "roll": 0.00 }
},
{
"time": "6/14/2012 9:14:40 AM",
"avgcovariancedeterminant": "190528800053.452",
"ins": {"x": 22540.00, "y": -9180.00, "z": 1470.00, "yaw": 1.61, "roll": 0.00, "pitch": 0.01 },
"slam": {"x": 22790.59, "y": -9151.81, "yaw": 1.62 },
"groundtruth": {"x": 22620.00, "y": -9210.00, "z": 1720.00, "yaw": 1.62, "pitch": 0.01, "roll": 0.00 }
},
{
"time": "6/14/2012 9:14:40 AM",
"avgcovariancedeterminant": "184668649330.854",
"ins": {"x": 22510.00, "y": -8810.00, "z": 1460.00, "yaw": 1.61, "roll": 0.00, "pitch": 0.04 },
"slam": {"x": 22771.43, "y": -8793.53, "yaw": 1.63 },
"groundtruth": {"x": 22600.00, "y": -8740.00, "z": 1720.00, "yaw": 1.63, "pitch": 0.01, "roll": 0.00 }
},
{
"time": "6/14/2012 9:14:40 AM",
"avgcovariancedeterminant": "363235997886.08",
"ins": {"x": 22500.00, "y": -8460.00, "z": 1460.00, "yaw": 1.62, "roll": 0.00, "pitch": 0.01 },
"slam": {"x": 22760.69, "y": -8459.19, "yaw": 1.63 },
"groundtruth": {"x": 22580.00, "y": -8510.00, "z": 1720.00, "yaw": 1.63, "pitch": 0.01, "roll": 0.00 }
},
{
"time": "6/14/2012 9:14:40 AM",
"avgcovariancedeterminant": "352148104386.387",
"ins": {"x": 22480.00, "y": -8020.00, "z": 1460.00, "yaw": 1.62, "roll": 0.00, "pitch": 0.01 },
"slam": {"x": 22735.79, "y": -8025.70, "yaw": 1.63 },
"groundtruth": {"x": 22550.00, "y": -8050.00, "z": 1720.00, "yaw": 1.63, "pitch": 0.00, "roll": 0.00 }
},
{
"time": "6/14/2012 9:14:42 AM",
"avgcovariancedeterminant": "342311944496.826",
"ins": {"x": 22470.00, "y": -7560.00, "z": 1450.00, "yaw": 1.61, "roll": 6.28, "pitch": 0.05 },
"slam": {"x": 22719.45, "y": -7561.05, "yaw": 1.62 },
"groundtruth": {"x": 22530.00, "y": -7590.00, "z": 1710.00, "yaw": 1.62, "pitch": 0.04, "roll": 0.00 }
},
{
"time": "6/14/2012 9:14:42 AM",
"avgcovariancedeterminant": "332617352141.093",
"ins": {"x": 22480.00, "y": -7080.00, "z": 1480.00, "yaw": 1.60, "roll": 0.00, "pitch": 0.01 },
"slam": {"x": 22701.56, "y": -7081.36, "yaw": 1.61 },
"groundtruth": {"x": 22510.00, "y": -7110.00, "z": 1720.00, "yaw": 1.61, "pitch": 0.00, "roll": 0.00 }
},
{
"time": "6/14/2012 9:14:42 AM",
"avgcovariancedeterminant": "328150661904.241",
"ins": {"x": 22470.00, "y": -6920.00, "z": 1470.00, "yaw": 1.61, "roll": 0.00, "pitch": 0.03 },
"slam": {"x": 22692.17, "y": -6846.02, "yaw": 1.64 },
"groundtruth": {"x": 22490.00, "y": -6870.00, "z": 1720.00, "yaw": 1.63, "pitch": 0.00, "roll": 0.00 }
},
{
"time": "6/14/2012 9:14:44 AM",
"avgcovariancedeterminant": "606424582873.041",
"ins": {"x": 22400.00, "y": -5530.00, "z": 1470.00, "yaw": 1.62, "roll": 0.00, "pitch": 0.02 },
"slam": {"x": 22622.79, "y": -5479.25, "yaw": 1.64 },
"groundtruth": {"x": 22410.00, "y": -5480.00, "z": 1720.00, "yaw": 1.64, "pitch": 0.00, "roll": 0.00 }
},
{
"time": "6/14/2012 9:14:44 AM",
"avgcovariancedeterminant": "299686232453.466",
"ins": {"x": 22350.00, "y": -5200.00, "z": 1450.00, "yaw": 1.63, "roll": 0.00, "pitch": 0.02 },
"slam": {"x": 22608.52, "y": -5213.21, "yaw": 1.64 },
"groundtruth": {"x": 22390.00, "y": -5230.00, "z": 1720.00, "yaw": 1.64, "pitch": 0.01, "roll": 0.00 }
},
{
"time": "6/14/2012 9:14:45 AM",
"avgcovariancedeterminant": "296052165153.757",
"ins": {"x": 22350.00, "y": -5040.00, "z": 1440.00, "yaw": 1.63, "roll": 0.00, "pitch": 0.01 },
"slam": {"x": 22594.55, "y": -4982.16, "yaw": 1.64 },
"groundtruth": {"x": 22370.00, "y": -5000.00, "z": 1720.00, "yaw": 1.64, "pitch": 0.00, "roll": 0.00 }
},
{
"time": "6/14/2012 9:14:45 AM",
"avgcovariancedeterminant": "292397180995.594",
"ins": {"x": 22340.00, "y": -4740.00, "z": 1440.00, "yaw": 1.61, "roll": 0.00, "pitch": 0.02 },
"slam": {"x": 22585.61, "y": -4743.94, "yaw": 1.62 },
"groundtruth": {"x": 22360.00, "y": -4760.00, "z": 1710.00, "yaw": 1.62, "pitch": 0.01, "roll": 0.00 }
},
{
"time": "6/14/2012 9:14:46 AM",
"avgcovariancedeterminant": "289848822445.198",
"ins": {"x": 22320.00, "y": -4580.00, "z": 1440.00, "yaw": 1.61, "roll": 6.28, "pitch": 0.02 },
"slam": {"x": 22577.73, "y": -4516.51, "yaw": 1.63 },
"groundtruth": {"x": 22350.00, "y": -4540.00, "z": 1720.00, "yaw": 1.63, "pitch": 0.00, "roll": 0.00 }
},
{
"time": "6/14/2012 9:14:46 AM",
"avgcovariancedeterminant": "286878736135.069",
"ins": {"x": 22310.00, "y": -4260.00, "z": 1460.00, "yaw": 1.60, "roll": 0.00, "pitch": 0.01 },
"slam": {"x": 22568.89, "y": -4266.62, "yaw": 1.61 },
"groundtruth": {"x": 22340.00, "y": -4290.00, "z": 1720.00, "yaw": 1.61, "pitch": 0.00, "roll": 0.00 }
},
{
"time": "6/14/2012 9:14:46 AM",
"avgcovariancedeterminant": "284321900298.02",
"ins": {"x": 22300.00, "y": -4110.00, "z": 1450.00, "yaw": 1.58, "roll": 0.00, "pitch": 0.04 },
"slam": {"x": 22569.10, "y": -4042.40, "yaw": 1.58 },
"groundtruth": {"x": 22340.00, "y": -4060.00, "z": 1710.00, "yaw": 1.59, "pitch": 0.03, "roll": 0.00 }
},
{
"time": "6/14/2012 9:14:46 AM",
"avgcovariancedeterminant": "281815480301.824",
"ins": {"x": 22290.00, "y": -3800.00, "z": 1460.00, "yaw": 1.61, "roll": 6.28, "pitch": 0.01 },
"slam": {"x": 22560.37, "y": -3798.42, "yaw": 1.62 },
"groundtruth": {"x": 22320.00, "y": -3820.00, "z": 1720.00, "yaw": 1.62, "pitch": 0.00, "roll": 0.00 }
},
{
"time": "6/14/2012 9:14:47 AM",
"avgcovariancedeterminant": "138717919070.538",
"ins": {"x": 22280.00, "y": -3310.00, "z": 1440.00, "yaw": 1.58, "roll": 0.00, "pitch": 0.01 },
"slam": {"x": 22556.36, "y": -3341.91, "yaw": 1.59 },
"groundtruth": {"x": 22320.00, "y": -3370.00, "z": 1720.00, "yaw": 1.59, "pitch": 0.00, "roll": 0.00 }
},
{
"time": "6/14/2012 9:14:50 AM",
"avgcovariancedeterminant": "278339948304.805",
"ins": {"x": 22280.00, "y": -3280.00, "z": 1440.00, "yaw": 1.74, "roll": 0.00, "pitch": 0.01 },
"slam": {"x": 22579.72, "y": -3307.41, "yaw": 1.83 },
"groundtruth": {"x": 22320.00, "y": -3330.00, "z": 1720.00, "yaw": 1.83, "pitch": 0.00, "roll": 0.00 }
},
{
"time": "6/14/2012 9:14:51 AM",
"avgcovariancedeterminant": "418995549407.527",
"ins": {"x": 22280.00, "y": -3270.00, "z": 1450.00, "yaw": 2.28, "roll": 6.28, "pitch": 0.01 },
"slam": {"x": 22607.99, "y": -3284.47, "yaw": 2.29 },
"groundtruth": {"x": 22320.00, "y": -3330.00, "z": 1720.00, "yaw": 2.30, "pitch": 0.00, "roll": 0.00 }
},
{
"time": "6/14/2012 9:14:52 AM",
"avgcovariancedeterminant": "277849052973.532",
"ins": {"x": 22230.00, "y": -3240.00, "z": 1450.00, "yaw": 2.61, "roll": 6.28, "pitch": 0.01 },
"slam": {"x": 22580.62, "y": -3228.26, "yaw": 2.68 },
"groundtruth": {"x": 22270.00, "y": -3300.00, "z": 1720.00, "yaw": 2.68, "pitch": 0.00, "roll": 0.00 }
},
{
"time": "6/14/2012 9:14:53 AM",
"avgcovariancedeterminant": "276405157138.269",
"ins": {"x": 22200.00, "y": -3220.00, "z": 1450.00, "yaw": 2.95, "roll": 0.00, "pitch": 0.01 },
"slam": {"x": 22271.23, "y": -3182.06, "yaw": 2.98 },
"groundtruth": {"x": 22240.00, "y": -3280.00, "z": 1720.00, "yaw": 2.98, "pitch": 0.00, "roll": 0.00 }
},
{
"time": "6/14/2012 9:14:55 AM",
"avgcovariancedeterminant": "391592488317.104",
"ins": {"x": 21940.00, "y": -3170.00, "z": 1440.00, "yaw": 2.94, "roll": 0.00, "pitch": 0.02 },
"slam": {"x": 21949.19, "y": -3123.91, "yaw": 2.98 },
"groundtruth": {"x": 21920.00, "y": -3220.00, "z": 1720.00, "yaw": 2.98, "pitch": 0.00, "roll": 0.00 }
},
{
"time": "6/14/2012 9:14:56 AM",
"avgcovariancedeterminant": "500971301926.025",
"ins": {"x": 21620.00, "y": -3120.00, "z": 1450.00, "yaw": 2.94, "roll": 6.28, "pitch": 0.02 },
"slam": {"x": 21722.43, "y": -3083.18, "yaw": 2.97 },
"groundtruth": {"x": 21690.00, "y": -3180.00, "z": 1720.00, "yaw": 2.98, "pitch": 0.01, "roll": 0.00 }
},
{
"time": "6/14/2012 9:14:56 AM",
"avgcovariancedeterminant": "479569855075.686",
"ins": {"x": 21470.00, "y": -3100.00, "z": 1440.00, "yaw": 2.93, "roll": 0.00, "pitch": 0.04 },
"slam": {"x": 21491.66, "y": -3040.54, "yaw": 2.97 },
"groundtruth": {"x": 21460.00, "y": -3140.00, "z": 1710.00, "yaw": 2.97, "pitch": 0.02, "roll": 0.00 }
},
{
"time": "6/14/2012 9:14:56 AM",
"avgcovariancedeterminant": "459753605986.174",
"ins": {"x": 21190.00, "y": -3030.00, "z": 1440.00, "yaw": 2.95, "roll": 6.28, "pitch": 0.01 },
"slam": {"x": 21266.44, "y": -3002.27, "yaw": 2.99 },
"groundtruth": {"x": 21230.00, "y": -3110.00, "z": 1720.00, "yaw": 2.99, "pitch": 0.01, "roll": 0.00 }
},
{
"time": "6/14/2012 9:14:56 AM",
"avgcovariancedeterminant": "439540407118.081",
"ins": {"x": 21020.00, "y": -3000.00, "z": 1430.00, "yaw": 2.96, "roll": 6.28, "pitch": 0.01 },
"slam": {"x": 21030.11, "y": -2966.07, "yaw": 2.99 },
"groundtruth": {"x": 20990.00, "y": -3070.00, "z": 1720.00, "yaw": 2.99, "pitch": 0.02, "roll": 0.00 }
},
{
"time": "6/14/2012 9:14:56 AM",
"avgcovariancedeterminant": "420186423519.596",
"ins": {"x": 20720.00, "y": -2940.00, "z": 1430.00, "yaw": 2.95, "roll": 0.00, "pitch": 0.01 },
"slam": {"x": 20786.14, "y": -2924.88, "yaw": 2.98 },
"groundtruth": {"x": 20760.00, "y": -3040.00, "z": 1720.00, "yaw": 2.98, "pitch": 0.00, "roll": 0.00 }
},
{
"time": "6/14/2012 9:14:56 AM",
"avgcovariancedeterminant": "502554746138.928",
"ins": {"x": 20570.00, "y": -2930.00, "z": 1430.00, "yaw": 2.96, "roll": 0.00, "pitch": 0.01 },
"slam": {"x": 20570.21, "y": -2890.52, "yaw": 3.00 },
"groundtruth": {"x": 20530.00, "y": -3000.00, "z": 1720.00, "yaw": 3.00, "pitch": 0.01, "roll": 0.00 }
},
{
"time": "6/14/2012 9:14:58 AM",
"avgcovariancedeterminant": "223099197447.499",
"ins": {"x": 20250.00, "y": -2880.00, "z": 1430.00, "yaw": 2.96, "roll": 0.00, "pitch": 0.02 },
"slam": {"x": 20271.58, "y": -2853.26, "yaw": 2.99 },
"groundtruth": {"x": 20290.00, "y": -2970.00, "z": 1710.00, "yaw": 2.99, "pitch": 0.02, "roll": 0.00 }
},
{
"time": "6/14/2012 9:14:58 AM",
"avgcovariancedeterminant": "262675599387.028",
"ins": {"x": 19790.00, "y": -2800.00, "z": 1450.00, "yaw": 2.96, "roll": 0.00, "pitch": 0.01 },
"slam": {"x": 19788.38, "y": -2773.66, "yaw": 2.99 },
"groundtruth": {"x": 19820.00, "y": -2900.00, "z": 1720.00, "yaw": 2.99, "pitch": 0.01, "roll": 0.00 }
},
{
"time": "6/14/2012 9:14:58 AM",
"avgcovariancedeterminant": "251409139215.97",
"ins": {"x": 19640.00, "y": -2780.00, "z": 1460.00, "yaw": 2.96, "roll": 0.00, "pitch": 0.01 },
"slam": {"x": 19563.19, "y": -2738.06, "yaw": 2.99 },
"groundtruth": {"x": 19600.00, "y": -2860.00, "z": 1720.00, "yaw": 2.99, "pitch": 0.01, "roll": 0.00 }
},
{
"time": "6/14/2012 9:14:58 AM",
"avgcovariancedeterminant": "239025223462.707",
"ins": {"x": 19310.00, "y": -2730.00, "z": 1480.00, "yaw": 2.94, "roll": 0.00, "pitch": 0.00 },
"slam": {"x": 19319.54, "y": -2693.78, "yaw": 2.97 },
"groundtruth": {"x": 19360.00, "y": -2820.00, "z": 1720.00, "yaw": 2.97, "pitch": 0.00, "roll": 0.00 }
},
{
"time": "6/14/2012 9:14:58 AM",
"avgcovariancedeterminant": "152416514816.107",
"ins": {"x": 19170.00, "y": -2700.00, "z": 1460.00, "yaw": 2.93, "roll": 0.00, "pitch": 0.02 },
"slam": {"x": 19109.95, "y": -2654.39, "yaw": 2.97 },
"groundtruth": {"x": 19140.00, "y": -2780.00, "z": 1710.00, "yaw": 2.97, "pitch": 0.04, "roll": 0.00 }
},
{
"time": "6/14/2012 9:14:59 AM",
"avgcovariancedeterminant": "145066157306.982",
"ins": {"x": 18820.00, "y": -2650.00, "z": 1470.00, "yaw": 2.96, "roll": 0.00, "pitch": 0.00 },
"slam": {"x": 18811.65, "y": -2616.69, "yaw": 2.99 },
"groundtruth": {"x": 18900.00, "y": -2750.00, "z": 1720.00, "yaw": 2.99, "pitch": 0.00, "roll": 0.00 }
},
{
"time": "6/14/2012 9:15:00 AM",
"avgcovariancedeterminant": "131387791047.472",
"ins": {"x": 18350.00, "y": -2530.00, "z": 1480.00, "yaw": 2.94, "roll": 0.00, "pitch": 0.01 },
"slam": {"x": 18327.43, "y": -2529.57, "yaw": 2.97 },
"groundtruth": {"x": 18430.00, "y": -2670.00, "z": 1720.00, "yaw": 2.98, "pitch": 0.01, "roll": 0.00 }
},
{
"time": "6/14/2012 9:15:00 AM",
"avgcovariancedeterminant": "187101803596.65",
"ins": {"x": 18200.00, "y": -2510.00, "z": 1490.00, "yaw": 2.95, "roll": 0.00, "pitch": 0.00 },
"slam": {"x": 18091.56, "y": -2489.96, "yaw": 2.98 },
"groundtruth": {"x": 18200.00, "y": -2630.00, "z": 1720.00, "yaw": 2.98, "pitch": 0.01, "roll": 0.00 }
},
{
"time": "6/14/2012 9:15:00 AM",
"avgcovariancedeterminant": "177743380988.31",
"ins": {"x": 17880.00, "y": -2440.00, "z": 1480.00, "yaw": 2.93, "roll": 6.28, "pitch": 0.00 },
"slam": {"x": 17861.97, "y": -2444.34, "yaw": 2.96 },
"groundtruth": {"x": 17970.00, "y": -2590.00, "z": 1720.00, "yaw": 2.96, "pitch": 0.01, "roll": 0.00 }
},
{
"time": "6/14/2012 9:15:01 AM",
"avgcovariancedeterminant": "213962363274.431",
"ins": {"x": 17410.00, "y": -2370.00, "z": 1480.00, "yaw": 2.95, "roll": 0.00, "pitch": 6.28 },
"slam": {"x": 17423.95, "y": -2363.47, "yaw": 2.98 },
"groundtruth": {"x": 17500.00, "y": -2510.00, "z": 1720.00, "yaw": 2.98, "pitch": 0.00, "roll": 0.00 }
},
{
"time": "6/14/2012 9:15:01 AM",
"avgcovariancedeterminant": "152440830800.949",
"ins": {"x": 17240.00, "y": -2320.00, "z": 1470.00, "yaw": 2.94, "roll": 0.00, "pitch": 0.01 },
"slam": {"x": 17197.88, "y": -2321.97, "yaw": 2.97 },
"groundtruth": {"x": 17280.00, "y": -2470.00, "z": 1720.00, "yaw": 2.97, "pitch": 0.00, "roll": 0.00 }
},
{
"time": "6/14/2012 9:15:01 AM",
"avgcovariancedeterminant": "143966840357.307",
"ins": {"x": 16940.00, "y": -2250.00, "z": 1480.00, "yaw": 2.93, "roll": 0.00, "pitch": 6.28 },
"slam": {"x": 16951.22, "y": -2273.34, "yaw": 2.96 },
"groundtruth": {"x": 17030.00, "y": -2430.00, "z": 1720.00, "yaw": 2.96, "pitch": 0.00, "roll": 0.00 }
},
{
"time": "6/14/2012 9:15:02 AM",
"avgcovariancedeterminant": "136430706120.283",
"ins": {"x": 16790.00, "y": -2230.00, "z": 1480.00, "yaw": 2.94, "roll": 0.00, "pitch": 0.01 },
"slam": {"x": 16726.35, "y": -2232.24, "yaw": 2.97 },
"groundtruth": {"x": 16800.00, "y": -2390.00, "z": 1710.00, "yaw": 2.97, "pitch": 0.02, "roll": 0.00 }
},
{
"time": "6/14/2012 9:15:02 AM",
"avgcovariancedeterminant": "129283684053.988",
"ins": {"x": 16480.00, "y": -2180.00, "z": 1480.00, "yaw": 2.93, "roll": 6.28, "pitch": 0.00 },
"slam": {"x": 16498.05, "y": -2190.59, "yaw": 2.96 },
"groundtruth": {"x": 16570.00, "y": -2350.00, "z": 1720.00, "yaw": 2.97, "pitch": 0.00, "roll": 0.00 }
},
{
"time": "6/14/2012 9:15:03 AM",
"avgcovariancedeterminant": "117227467867.378",
"ins": {"x": 16070.00, "y": -2140.00, "z": 1490.00, "yaw": 2.92, "roll": 0.00, "pitch": 6.28 },
"slam": {"x": 16093.97, "y": -2057.22, "yaw": 2.95 },
"groundtruth": {"x": 16170.00, "y": -2270.00, "z": 1720.00, "yaw": 2.96, "pitch": 0.00, "roll": 0.00 }
},
{
"time": "6/14/2012 9:15:06 AM",
"avgcovariancedeterminant": "115827193468.668",
"ins": {"x": 16030.00, "y": -2130.00, "z": 1490.00, "yaw": 3.12, "roll": 6.28, "pitch": 6.28 },
"slam": {"x": 16051.21, "y": -2055.24, "yaw": 3.15 },
"groundtruth": {"x": 16120.00, "y": -2270.00, "z": 1720.00, "yaw": -3.13, "pitch": 0.00, "roll": 0.00 }
},
{
"time": "6/14/2012 9:15:07 AM",
"avgcovariancedeterminant": "114839450522.793",
"ins": {"x": 15990.00, "y": -2130.00, "z": 1490.00, "yaw": 3.45, "roll": 0.00, "pitch": 6.28 },
"slam": {"x": 16009.59, "y": -2026.33, "yaw": 3.52 },
"groundtruth": {"x": 16090.00, "y": -2270.00, "z": 1720.00, "yaw": -2.76, "pitch": 0.00, "roll": 0.00 }
},
{
"time": "6/14/2012 9:15:08 AM",
"avgcovariancedeterminant": "153670957298.314",
"ins": {"x": 16040.00, "y": -2100.00, "z": 1490.00, "yaw": 3.79, "roll": 0.00, "pitch": 6.28 },
"slam": {"x": 16046.54, "y": -1969.52, "yaw": 3.83 },
"groundtruth": {"x": 16140.00, "y": -2240.00, "z": 1720.00, "yaw": -2.46, "pitch": 0.00, "roll": 0.00 }
},
{
"time": "6/14/2012 9:15:08 AM",
"avgcovariancedeterminant": "133958473287.89",
"ins": {"x": 16050.00, "y": -2110.00, "z": 1490.00, "yaw": 4.06, "roll": 6.28, "pitch": 6.28 },
"slam": {"x": 16025.96, "y": -1969.12, "yaw": 4.19 },
"groundtruth": {"x": 16140.00, "y": -2260.00, "z": 1720.00, "yaw": -2.09, "pitch": 0.00, "roll": 0.00 }
},
{
"time": "6/14/2012 9:15:10 AM",
"avgcovariancedeterminant": "114576965260.514",
"ins": {"x": 16030.00, "y": -2150.00, "z": 1490.00, "yaw": 4.28, "roll": 6.28, "pitch": 0.01 },
"slam": {"x": 16006.85, "y": -1994.71, "yaw": 4.33 },
"groundtruth": {"x": 16130.00, "y": -2290.00, "z": 1720.00, "yaw": -1.95, "pitch": 0.01, "roll": 0.00 }
},
{
"time": "6/14/2012 9:15:10 AM",
"avgcovariancedeterminant": "150299484186.748",
"ins": {"x": 15970.00, "y": -2270.00, "z": 1490.00, "yaw": 4.26, "roll": 0.00, "pitch": 0.00 },
"slam": {"x": 15917.83, "y": -2193.89, "yaw": 4.31 },
"groundtruth": {"x": 16040.00, "y": -2490.00, "z": 1720.00, "yaw": -1.97, "pitch": 0.00, "roll": 0.00 }
},
{
"time": "6/14/2012 9:15:10 AM",
"avgcovariancedeterminant": "111411591483.078",
"ins": {"x": 15850.00, "y": -2580.00, "z": 1510.00, "yaw": 4.27, "roll": 0.00, "pitch": 0.01 },
"slam": {"x": 15820.58, "y": -2423.95, "yaw": 4.32 },
"groundtruth": {"x": 15940.00, "y": -2720.00, "z": 1720.00, "yaw": -1.96, "pitch": 0.02, "roll": 0.00 }
},
{
"time": "6/14/2012 9:15:10 AM",
"avgcovariancedeterminant": "109969253242.319",
"ins": {"x": 15800.00, "y": -2720.00, "z": 1520.00, "yaw": 4.27, "roll": 0.00, "pitch": 6.28 },
"slam": {"x": 15729.96, "y": -2632.20, "yaw": 4.31 },
"groundtruth": {"x": 15860.00, "y": -2930.00, "z": 1720.00, "yaw": -1.97, "pitch": 0.01, "roll": 0.00 }
},
{
"time": "6/14/2012 9:15:10 AM",
"avgcovariancedeterminant": "108381135911.412",
"ins": {"x": 15640.00, "y": -3000.00, "z": 1530.00, "yaw": 4.26, "roll": 6.28, "pitch": 0.00 },
"slam": {"x": 15631.86, "y": -2851.33, "yaw": 4.30 },
"groundtruth": {"x": 15760.00, "y": -3150.00, "z": 1720.00, "yaw": -1.98, "pitch": 0.01, "roll": 0.00 }
},
{
"time": "6/14/2012 9:15:10 AM",
"avgcovariancedeterminant": "107305494923.123",
"ins": {"x": 15580.00, "y": -3140.00, "z": 1520.00, "yaw": 4.26, "roll": 0.00, "pitch": 0.01 },
"slam": {"x": 15540.09, "y": -3064.39, "yaw": 4.31 },
"groundtruth": {"x": 15670.00, "y": -3370.00, "z": 1720.00, "yaw": -1.97, "pitch": 0.00, "roll": 0.00 }
},
{
"time": "6/14/2012 9:15:11 AM",
"avgcovariancedeterminant": "141243213930.052",
"ins": {"x": 15460.00, "y": -3440.00, "z": 1500.00, "yaw": 4.24, "roll": 0.00, "pitch": 0.00 },
"slam": {"x": 15437.79, "y": -3289.33, "yaw": 4.29 },
"groundtruth": {"x": 15570.00, "y": -3590.00, "z": 1720.00, "yaw": -1.99, "pitch": 0.00, "roll": 0.00 }
},
{
"time": "6/14/2012 9:15:11 AM",
"avgcovariancedeterminant": "104646825617.756",
"ins": {"x": 15390.00, "y": -3580.00, "z": 1500.00, "yaw": 4.25, "roll": 6.28, "pitch": 0.00 },
"slam": {"x": 15339.05, "y": -3505.12, "yaw": 4.30 },
"groundtruth": {"x": 15480.00, "y": -3810.00, "z": 1720.00, "yaw": -1.98, "pitch": 0.00, "roll": 0.00 }
},
{
"time": "6/14/2012 9:15:12 AM",
"avgcovariancedeterminant": "138462960598.912",
"ins": {"x": 15250.00, "y": -3870.00, "z": 1510.00, "yaw": 4.25, "roll": 0.00, "pitch": 6.28 },
"slam": {"x": 15247.27, "y": -3712.01, "yaw": 4.30 },
"groundtruth": {"x": 15390.00, "y": -4020.00, "z": 1720.00, "yaw": -1.98, "pitch": 0.00, "roll": 0.00 }
},
{
"time": "6/14/2012 9:15:12 AM",
"avgcovariancedeterminant": "171430977606.292",
"ins": {"x": 15190.00, "y": -4030.00, "z": 1500.00, "yaw": 4.25, "roll": 6.28, "pitch": 0.00 },
"slam": {"x": 15147.71, "y": -3937.40, "yaw": 4.30 },
"groundtruth": {"x": 15290.00, "y": -4250.00, "z": 1720.00, "yaw": -1.98, "pitch": 0.01, "roll": 0.00 }
},
{
"time": "6/14/2012 9:15:12 AM",
"avgcovariancedeterminant": "136131146525.683",
"ins": {"x": 15080.00, "y": -4310.00, "z": 1500.00, "yaw": 4.26, "roll": 0.00, "pitch": 0.00 },
"slam": {"x": 15054.98, "y": -4147.85, "yaw": 4.31 },
"groundtruth": {"x": 15200.00, "y": -4460.00, "z": 1720.00, "yaw": -1.97, "pitch": 0.00, "roll": 0.00 }
},
{
"time": "6/14/2012 9:15:12 AM",
"avgcovariancedeterminant": "168835500668.897",
"ins": {"x": 15020.00, "y": -4450.00, "z": 1490.00, "yaw": 4.26, "roll": 0.00, "pitch": 0.00 },
"slam": {"x": 14953.59, "y": -4377.40, "yaw": 4.30 },
"groundtruth": {"x": 15100.00, "y": -4690.00, "z": 1720.00, "yaw": -1.97, "pitch": 0.01, "roll": 0.00 }
},
{
"time": "6/14/2012 9:15:13 AM",
"avgcovariancedeterminant": "66847334608.8726",
"ins": {"x": 14720.00, "y": -5160.00, "z": 1470.00, "yaw": 4.27, "roll": 6.28, "pitch": 0.00 },
"slam": {"x": 14667.52, "y": -5026.88, "yaw": 4.31 },
"groundtruth": {"x": 14830.00, "y": -5340.00, "z": 1720.00, "yaw": -1.97, "pitch": 0.00, "roll": 0.00 }
},
{
"time": "6/14/2012 9:15:14 AM",
"avgcovariancedeterminant": "99727525083.3362",
"ins": {"x": 14580.00, "y": -5460.00, "z": 1470.00, "yaw": 4.27, "roll": 0.00, "pitch": 6.28 },
"slam": {"x": 14533.47, "y": -5344.11, "yaw": 4.31 },
"groundtruth": {"x": 14700.00, "y": -5660.00, "z": 1720.00, "yaw": -1.97, "pitch": 0.00, "roll": 0.00 }
},
{
"time": "6/14/2012 9:15:18 AM",
"avgcovariancedeterminant": "134599802737.249",
"ins": {"x": 14570.00, "y": -5480.00, "z": 1470.00, "yaw": 3.84, "roll": 0.00, "pitch": 6.28 },
"slam": {"x": 14569.47, "y": -5377.58, "yaw": 3.85 },
"groundtruth": {"x": 14700.00, "y": -5680.00, "z": 1720.00, "yaw": -2.43, "pitch": 0.00, "roll": 0.00 }
},
{
"time": "6/14/2012 9:15:19 AM",
"avgcovariancedeterminant": "172245475949.077",
"ins": {"x": 14690.00, "y": -5420.00, "z": 1480.00, "yaw": 3.41, "roll": 0.00, "pitch": 6.28 },
"slam": {"x": 14689.02, "y": -5350.15, "yaw": 3.46 },
"groundtruth": {"x": 14810.00, "y": -5620.00, "z": 1720.00, "yaw": -2.82, "pitch": 0.00, "roll": 0.00 }
},
{
"time": "6/14/2012 9:15:20 AM",
"avgcovariancedeterminant": "174874191115.466",
"ins": {"x": 14740.00, "y": -5410.00, "z": 1480.00, "yaw": 3.24, "roll": 6.28, "pitch": 0.00 },
"slam": {"x": 14748.67, "y": -5359.15, "yaw": 3.28 },
"groundtruth": {"x": 14860.00, "y": -5610.00, "z": 1720.00, "yaw": -3.00, "pitch": 0.00, "roll": 0.00 }
},
{
"time": "6/14/2012 9:15:21 AM",
"avgcovariancedeterminant": "142565793243.297",
"ins": {"x": 14820.00, "y": -5420.00, "z": 1470.00, "yaw": 2.98, "roll": 0.00, "pitch": 0.00 },
"slam": {"x": 14829.04, "y": -5383.19, "yaw": 3.04 },
"groundtruth": {"x": 14940.00, "y": -5620.00, "z": 1720.00, "yaw": 3.04, "pitch": 0.00, "roll": 0.00 }
},
{
"time": "6/14/2012 9:15:22 AM",
"avgcovariancedeterminant": "143286278158.5",
"ins": {"x": 14830.00, "y": -5420.00, "z": 1470.00, "yaw": 2.77, "roll": 0.00, "pitch": 0.00 },
"slam": {"x": 14843.43, "y": -5402.45, "yaw": 2.78 },
"groundtruth": {"x": 14960.00, "y": -5620.00, "z": 1720.00, "yaw": 2.78, "pitch": 0.00, "roll": 0.00 }
},
{
"time": "6/14/2012 9:15:22 AM",
"avgcovariancedeterminant": "108867474567.607",
"ins": {"x": 14890.00, "y": -5440.00, "z": 1470.00, "yaw": 2.18, "roll": 6.28, "pitch": 6.28 },
"slam": {"x": 14866.34, "y": -5462.62, "yaw": 2.25 },
"groundtruth": {"x": 15010.00, "y": -5640.00, "z": 1720.00, "yaw": 2.25, "pitch": 0.00, "roll": 0.00 }
},
{
"time": "6/14/2012 9:15:23 AM",
"avgcovariancedeterminant": "108029070591.222",
"ins": {"x": 14880.00, "y": -5440.00, "z": 1470.00, "yaw": 1.85, "roll": 6.28, "pitch": 0.00 },
"slam": {"x": 14836.01, "y": -5476.64, "yaw": 1.88 },
"groundtruth": {"x": 15010.00, "y": -5640.00, "z": 1720.00, "yaw": 1.88, "pitch": 0.00, "roll": 0.00 }
},
{
"time": "6/14/2012 9:15:24 AM",
"avgcovariancedeterminant": "107796319096.712",
"ins": {"x": 14880.00, "y": -5450.00, "z": 1470.00, "yaw": 1.59, "roll": 0.00, "pitch": 6.28 },
"slam": {"x": 14820.07, "y": -5480.27, "yaw": 1.64 },
"groundtruth": {"x": 15010.00, "y": -5640.00, "z": 1720.00, "yaw": 1.64, "pitch": 0.00, "roll": 0.00 }
},
{
"time": "6/14/2012 9:15:25 AM",
"avgcovariancedeterminant": "107423290802.347",
"ins": {"x": 14880.00, "y": -5470.00, "z": 1470.00, "yaw": 1.37, "roll": 6.28, "pitch": 6.28 },
"slam": {"x": 14802.17, "y": -5503.34, "yaw": 1.43 },
"groundtruth": {"x": 15010.00, "y": -5670.00, "z": 1720.00, "yaw": 1.43, "pitch": 0.00, "roll": 0.00 }
},
{
"time": "6/14/2012 9:15:25 AM",
"avgcovariancedeterminant": "107171029268.318",
"ins": {"x": 14890.00, "y": -5450.00, "z": 1470.00, "yaw": 1.24, "roll": 0.00, "pitch": 6.28 },
"slam": {"x": 14795.08, "y": -5479.07, "yaw": 1.24 },
"groundtruth": {"x": 15020.00, "y": -5650.00, "z": 1720.00, "yaw": 1.25, "pitch": 0.00, "roll": 0.00 }
},
{
"time": "6/14/2012 9:15:25 AM",
"avgcovariancedeterminant": "142185698400.963",
"ins": {"x": 14890.00, "y": -5430.00, "z": 1470.00, "yaw": 1.03, "roll": 0.00, "pitch": 0.00 },
"slam": {"x": 14787.60, "y": -5459.49, "yaw": 1.08 },
"groundtruth": {"x": 15020.00, "y": -5630.00, "z": 1720.00, "yaw": 1.08, "pitch": 0.00, "roll": 0.00 }
},
{
"time": "6/14/2012 9:15:26 AM",
"avgcovariancedeterminant": "142215674203.694",
"ins": {"x": 14910.00, "y": -5410.00, "z": 1470.00, "yaw": 0.92, "roll": 6.28, "pitch": 6.28 },
"slam": {"x": 14792.27, "y": -5427.87, "yaw": 0.94 },
"groundtruth": {"x": 15030.00, "y": -5600.00, "z": 1720.00, "yaw": 0.94, "pitch": 0.00, "roll": 0.00 }
},
{
"time": "6/14/2012 9:15:26 AM",
"avgcovariancedeterminant": "219086952412.564",
"ins": {"x": 15050.00, "y": -5150.00, "z": 1470.00, "yaw": 0.89, "roll": 0.00, "pitch": 0.00 },
"slam": {"x": 15033.06, "y": -5106.51, "yaw": 0.93 },
"groundtruth": {"x": 15270.00, "y": -5280.00, "z": 1720.00, "yaw": 0.93, "pitch": 0.00, "roll": 0.00 }
},
{
"time": "6/14/2012 9:15:27 AM",
"avgcovariancedeterminant": "111556464965.244",
"ins": {"x": 15260.00, "y": -4880.00, "z": 1480.00, "yaw": 0.87, "roll": 0.00, "pitch": 0.00 },
"slam": {"x": 15174.73, "y": -4927.43, "yaw": 0.91 },
"groundtruth": {"x": 15410.00, "y": -5100.00, "z": 1720.00, "yaw": 0.92, "pitch": 0.00, "roll": 0.00 }
},
{
"time": "6/14/2012 9:15:27 AM",
"avgcovariancedeterminant": "151402043637.63",
"ins": {"x": 15380.00, "y": -4760.00, "z": 1470.00, "yaw": 0.87, "roll": 0.00, "pitch": 6.28 },
"slam": {"x": 15318.65, "y": -4739.84, "yaw": 0.92 },
"groundtruth": {"x": 15550.00, "y": -4910.00, "z": 1720.00, "yaw": 0.93, "pitch": 0.00, "roll": 0.00 }
},
{
"time": "6/14/2012 9:15:27 AM",
"avgcovariancedeterminant": "116859900743.913",
"ins": {"x": 15580.00, "y": -4480.00, "z": 1490.00, "yaw": 0.87, "roll": 0.00, "pitch": 6.28 },
"slam": {"x": 15471.66, "y": -4545.65, "yaw": 0.92 },
"groundtruth": {"x": 15700.00, "y": -4710.00, "z": 1720.00, "yaw": 0.92, "pitch": 0.00, "roll": 0.00 }
},
{
"time": "6/14/2012 9:15:27 AM",
"avgcovariancedeterminant": "118469492271.284",
"ins": {"x": 15680.00, "y": -4360.00, "z": 1490.00, "yaw": 0.86, "roll": 6.28, "pitch": 0.00 },
"slam": {"x": 15618.73, "y": -4360.93, "yaw": 0.91 },
"groundtruth": {"x": 15850.00, "y": -4520.00, "z": 1720.00, "yaw": 0.91, "pitch": 0.00, "roll": 0.00 }
},
{
"time": "6/14/2012 9:15:28 AM",
"avgcovariancedeterminant": "161268916764.459",
"ins": {"x": 15860.00, "y": -4110.00, "z": 1490.00, "yaw": 0.87, "roll": 0.00, "pitch": 6.28 },
"slam": {"x": 15758.56, "y": -4185.21, "yaw": 0.91 },
"groundtruth": {"x": 15990.00, "y": -4340.00, "z": 1720.00, "yaw": 0.92, "pitch": 0.00, "roll": 0.00 }
},
{
"time": "6/14/2012 9:15:28 AM",
"avgcovariancedeterminant": "123646923175.358",
"ins": {"x": 15990.00, "y": -3990.00, "z": 1500.00, "yaw": 0.87, "roll": 0.00, "pitch": 0.01 },
"slam": {"x": 15908.21, "y": -3992.38, "yaw": 0.91 },
"groundtruth": {"x": 16140.00, "y": -4150.00, "z": 1720.00, "yaw": 0.92, "pitch": 0.00, "roll": 0.00 }
},
{
"time": "6/14/2012 9:15:29 AM",
"avgcovariancedeterminant": "214939505421.644",
"ins": {"x": 16310.00, "y": -3610.00, "z": 1490.00, "yaw": 0.87, "roll": 0.00, "pitch": 0.00 },
"slam": {"x": 16196.76, "y": -3621.40, "yaw": 0.92 },
"groundtruth": {"x": 16420.00, "y": -3770.00, "z": 1720.00, "yaw": 0.92, "pitch": 0.00, "roll": 0.00 }
},
{
"time": "6/14/2012 9:15:30 AM",
"avgcovariancedeterminant": "182297398250.346",
"ins": {"x": 16700.00, "y": -3100.00, "z": 1480.00, "yaw": 0.78, "roll": 0.00, "pitch": 6.28 },
"slam": {"x": 16565.18, "y": -3142.87, "yaw": 0.82 },
"groundtruth": {"x": 16790.00, "y": -3300.00, "z": 1720.00, "yaw": 0.83, "pitch": 0.00, "roll": 0.00 }
},
{
"time": "6/14/2012 9:15:30 AM",
"avgcovariancedeterminant": "136810376869.523",
"ins": {"x": 16690.00, "y": -3110.00, "z": 1480.00, "yaw": 0.61, "roll": 0.00, "pitch": 6.28 },
"slam": {"x": 16556.80, "y": -3136.20, "yaw": 0.66 },
"groundtruth": {"x": 16790.00, "y": -3300.00, "z": 1720.00, "yaw": 0.66, "pitch": 0.00, "roll": 0.00 }
},
{
"time": "6/14/2012 9:15:31 AM",
"avgcovariancedeterminant": "180640964802.858",
"ins": {"x": 16690.00, "y": -3100.00, "z": 1480.00, "yaw": 0.26, "roll": 6.28, "pitch": 6.28 },
"slam": {"x": 16529.51, "y": -3111.01, "yaw": 0.30 },
"groundtruth": {"x": 16770.00, "y": -3300.00, "z": 1720.00, "yaw": 0.30, "pitch": 0.00, "roll": 0.00 }
},
{
"time": "6/14/2012 9:15:32 AM",
"avgcovariancedeterminant": "178462659586.701",
"ins": {"x": 16630.00, "y": -3110.00, "z": 1490.00, "yaw": 6.24, "roll": 6.28, "pitch": 6.28 },
"slam": {"x": 16473.92, "y": -3095.53, "yaw": 6.28 },
"groundtruth": {"x": 16720.00, "y": -3310.00, "z": 1720.00, "yaw": 0.00, "pitch": 0.00, "roll": 0.00 }
},
{
"time": "6/14/2012 9:15:32 AM",
"avgcovariancedeterminant": "177158486970.283",
"ins": {"x": 16610.00, "y": -3120.00, "z": 1480.00, "yaw": 6.11, "roll": 6.28, "pitch": 6.28 },
"slam": {"x": 16453.40, "y": -3088.80, "yaw": 6.14 },
"groundtruth": {"x": 16700.00, "y": -3310.00, "z": 1720.00, "yaw": -0.14, "pitch": 0.00, "roll": 0.00 }
},
{
"time": "6/14/2012 9:15:33 AM",
"avgcovariancedeterminant": "239074189302.312",
"ins": {"x": 16930.00, "y": -3190.00, "z": 1480.00, "yaw": 6.07, "roll": 0.00, "pitch": 0.00 },
"slam": {"x": 16771.50, "y": -3157.82, "yaw": 6.11 },
"groundtruth": {"x": 17020.00, "y": -3380.00, "z": 1720.00, "yaw": -0.17, "pitch": 0.00, "roll": 0.00 }
},
{
"time": "6/14/2012 9:15:34 AM",
"avgcovariancedeterminant": "202106534199.684",
"ins": {"x": 17090.00, "y": -3220.00, "z": 1480.00, "yaw": 6.08, "roll": 6.28, "pitch": 0.01 },
"slam": {"x": 17044.02, "y": -3200.65, "yaw": 6.12 },
"groundtruth": {"x": 17260.00, "y": -3420.00, "z": 1720.00, "yaw": -0.15, "pitch": 0.01, "roll": 0.00 }
},
{
"time": "6/14/2012 9:15:34 AM",
"avgcovariancedeterminant": "211916560610.115",
"ins": {"x": 17370.00, "y": -3270.00, "z": 1490.00, "yaw": 6.07, "roll": 0.00, "pitch": 0.02 },
"slam": {"x": 17368.40, "y": -3240.12, "yaw": 6.11 },
"groundtruth": {"x": 17470.00, "y": -3450.00, "z": 1720.00, "yaw": -0.17, "pitch": 0.02, "roll": 0.00 }
},
{
"time": "6/14/2012 9:15:34 AM",
"avgcovariancedeterminant": "236240296687.928",
"ins": {"x": 17820.00, "y": -3370.00, "z": 1480.00, "yaw": 6.08, "roll": 0.00, "pitch": 0.02 },
"slam": {"x": 17817.95, "y": -3331.17, "yaw": 6.12 },
"groundtruth": {"x": 17950.00, "y": -3540.00, "z": 1720.00, "yaw": -0.16, "pitch": 0.02, "roll": 0.00 }
},
{
"time": "6/14/2012 9:15:34 AM",
"avgcovariancedeterminant": "130506487432.865",
"ins": {"x": 18290.00, "y": -3450.00, "z": 1480.00, "yaw": 6.06, "roll": 6.28, "pitch": 0.00 },
"slam": {"x": 18276.35, "y": -3420.01, "yaw": 6.10 },
"groundtruth": {"x": 18400.00, "y": -3620.00, "z": 1720.00, "yaw": -0.18, "pitch": 0.00, "roll": 0.00 }
},
{
"time": "6/14/2012 9:15:36 AM",
"avgcovariancedeterminant": "216060577666.779",
"ins": {"x": 18770.00, "y": -3550.00, "z": 1470.00, "yaw": 6.06, "roll": 0.00, "pitch": 0.00 },
"slam": {"x": 18756.12, "y": -3506.00, "yaw": 6.10 },
"groundtruth": {"x": 18870.00, "y": -3700.00, "z": 1720.00, "yaw": -0.18, "pitch": 0.00, "roll": 0.00 }
},
{
"time": "6/14/2012 9:15:36 AM",
"avgcovariancedeterminant": "158675685908.663",
"ins": {"x": 19230.00, "y": -3660.00, "z": 1470.00, "yaw": 6.05, "roll": 0.00, "pitch": 0.00 },
"slam": {"x": 19234.56, "y": -3604.78, "yaw": 6.09 },
"groundtruth": {"x": 19340.00, "y": -3790.00, "z": 1720.00, "yaw": -0.19, "pitch": 0.00, "roll": 0.00 }
},
{
"time": "6/14/2012 9:15:36 AM",
"avgcovariancedeterminant": "261132485097.268",
"ins": {"x": 19670.00, "y": -3750.00, "z": 1480.00, "yaw": 6.04, "roll": 0.00, "pitch": 0.03 },
"slam": {"x": 19673.84, "y": -3700.23, "yaw": 6.08 },
"groundtruth": {"x": 19790.00, "y": -3880.00, "z": 1710.00, "yaw": -0.20, "pitch": 0.02, "roll": 0.00 }
},
{
"time": "6/14/2012 9:15:37 AM",
"avgcovariancedeterminant": "274322115952.507",
"ins": {"x": 19840.00, "y": -3780.00, "z": 1460.00, "yaw": 6.04, "roll": 0.00, "pitch": 0.02 },
"slam": {"x": 19924.25, "y": -3752.97, "yaw": 6.08 },
"groundtruth": {"x": 20040.00, "y": -3930.00, "z": 1720.00, "yaw": -0.20, "pitch": 0.01, "roll": 0.00 }
},
{
"time": "6/14/2012 9:15:38 AM",
"avgcovariancedeterminant": "191334779410.065",
"ins": {"x": 20140.00, "y": -3840.00, "z": 1470.00, "yaw": 6.05, "roll": 6.28, "pitch": 0.01 },
"slam": {"x": 20145.00, "y": -3798.95, "yaw": 6.09 },
"groundtruth": {"x": 20260.00, "y": -3970.00, "z": 1720.00, "yaw": -0.19, "pitch": 0.01, "roll": 0.00 }
},
{
"time": "6/14/2012 9:15:38 AM",
"avgcovariancedeterminant": "100163877098.242",
"ins": {"x": 20280.00, "y": -3870.00, "z": 1460.00, "yaw": 6.04, "roll": 0.00, "pitch": 0.04 },
"slam": {"x": 20377.26, "y": -3848.78, "yaw": 6.08 },
"groundtruth": {"x": 20490.00, "y": -4020.00, "z": 1720.00, "yaw": -0.20, "pitch": 0.01, "roll": 0.00 }
},
{
"time": "6/14/2012 9:15:50 AM",
"avgcovariancedeterminant": "148530288303.39",
"ins": {"x": 21270.00, "y": -7920.00, "z": 1410.00, "yaw": 4.70, "roll": 0.00, "pitch": 0.02 },
"slam": {"x": 21270.00, "y": -7920.00, "yaw": 4.70 },
"groundtruth": {"x": 21540.00, "y": -8080.00, "z": 1710.00, "yaw": -1.53, "pitch": 0.03, "roll": 0.00 }
},
{
"time": "6/14/2012 9:15:50 AM",
"avgcovariancedeterminant": "150583546681.188",
"ins": {"x": 21290.00, "y": -8220.00, "z": 1410.00, "yaw": 4.68, "roll": 0.01, "pitch": 0.02 },
"slam": {"x": 21253.18, "y": -8231.21, "yaw": 4.67 },
"groundtruth": {"x": 21540.00, "y": -8310.00, "z": 1710.00, "yaw": -1.55, "pitch": 0.02, "roll": 0.00 }
},
{
"time": "6/14/2012 9:15:51 AM",
"avgcovariancedeterminant": "155884672100.601",
"ins": {"x": 21270.00, "y": -8670.00, "z": 1410.00, "yaw": 4.71, "roll": 0.00, "pitch": 0.01 },
"slam": {"x": 21242.91, "y": -8638.37, "yaw": 4.70 },
"groundtruth": {"x": 21560.00, "y": -8790.00, "z": 1720.00, "yaw": -1.52, "pitch": 0.00, "roll": 0.00 }
},
{
"time": "6/14/2012 9:15:51 AM",
"avgcovariancedeterminant": "161025265390.562",
"ins": {"x": 21300.00, "y": -9140.00, "z": 1380.00, "yaw": 4.70, "roll": 6.28, "pitch": 0.03 },
"slam": {"x": 21221.91, "y": -9136.26, "yaw": 4.69 },
"groundtruth": {"x": 21570.00, "y": -9260.00, "z": 1710.00, "yaw": -1.53, "pitch": 0.02, "roll": 0.00 }
},
{
"time": "6/14/2012 9:15:51 AM",
"avgcovariancedeterminant": "166617559025.854",
"ins": {"x": 21340.00, "y": -9600.00, "z": 1380.00, "yaw": 4.70, "roll": 0.00, "pitch": 0.02 },
"slam": {"x": 21210.88, "y": -9581.17, "yaw": 4.69 },
"groundtruth": {"x": 21590.00, "y": -9730.00, "z": 1720.00, "yaw": -1.54, "pitch": 0.01, "roll": 0.00 }
},
{
"time": "6/14/2012 9:15:53 AM",
"avgcovariancedeterminant": "172521524506.551",
"ins": {"x": 21350.00, "y": -10070.00, "z": 1400.00, "yaw": 4.70, "roll": 6.28, "pitch": 0.02 },
"slam": {"x": 21196.01, "y": -10072.85, "yaw": 4.69 },
"groundtruth": {"x": 21610.00, "y": -10200.00, "z": 1720.00, "yaw": -1.54, "pitch": 0.01, "roll": 0.00 }
},
{
"time": "6/14/2012 9:15:53 AM",
"avgcovariancedeterminant": "178999496028.843",
"ins": {"x": 21350.00, "y": -10550.00, "z": 1390.00, "yaw": 4.69, "roll": 0.00, "pitch": 0.03 },
"slam": {"x": 21180.83, "y": -10542.82, "yaw": 4.68 },
"groundtruth": {"x": 21630.00, "y": -10670.00, "z": 1710.00, "yaw": -1.54, "pitch": 0.02, "roll": 0.00 }
},
{
"time": "6/14/2012 9:15:53 AM",
"avgcovariancedeterminant": "185922403977.624",
"ins": {"x": 21380.00, "y": -11020.00, "z": 1380.00, "yaw": 4.70, "roll": 0.00, "pitch": 0.01 },
"slam": {"x": 21168.07, "y": -10994.13, "yaw": 4.69 },
"groundtruth": {"x": 21640.00, "y": -11130.00, "z": 1720.00, "yaw": -1.53, "pitch": 0.01, "roll": 0.00 }
},
{
"time": "6/14/2012 9:15:54 AM",
"avgcovariancedeterminant": "192726510107.093",
"ins": {"x": 21370.00, "y": -11520.00, "z": 1380.00, "yaw": 4.69, "roll": 6.28, "pitch": 0.02 },
"slam": {"x": 21141.50, "y": -11513.36, "yaw": 4.69 },
"groundtruth": {"x": 21650.00, "y": -11600.00, "z": 1720.00, "yaw": -1.54, "pitch": 0.01, "roll": 0.00 }
},
{
"time": "6/14/2012 9:15:55 AM",
"avgcovariancedeterminant": "200036819894.171",
"ins": {"x": 21370.00, "y": -11990.00, "z": 1380.00, "yaw": 4.67, "roll": 6.28, "pitch": 0.01 },
"slam": {"x": 21116.93, "y": -11968.22, "yaw": 4.67 },
"groundtruth": {"x": 21660.00, "y": -12080.00, "z": 1720.00, "yaw": -1.56, "pitch": 0.00, "roll": 0.00 }
},
{
"time": "6/14/2012 9:15:55 AM",
"avgcovariancedeterminant": "208185939678.928",
"ins": {"x": 21380.00, "y": -12460.00, "z": 1400.00, "yaw": 4.70, "roll": 0.00, "pitch": 0.01 },
"slam": {"x": 21104.12, "y": -12446.69, "yaw": 4.69 },
"groundtruth": {"x": 21680.00, "y": -12540.00, "z": 1720.00, "yaw": -1.53, "pitch": 0.00, "roll": 0.00 }
},
{
"time": "6/14/2012 9:15:56 AM",
"avgcovariancedeterminant": "216661486383.08",
"ins": {"x": 21390.00, "y": -12910.00, "z": 1400.00, "yaw": 4.72, "roll": 0.00, "pitch": 0.02 },
"slam": {"x": 21095.66, "y": -12904.31, "yaw": 4.71 },
"groundtruth": {"x": 21700.00, "y": -13000.00, "z": 1720.00, "yaw": -1.52, "pitch": 0.01, "roll": 0.00 }
},
{
"time": "6/14/2012 9:15:56 AM",
"avgcovariancedeterminant": "225689635135.986",
"ins": {"x": 21400.00, "y": -13390.00, "z": 1400.00, "yaw": 4.71, "roll": 0.00, "pitch": 0.02 },
"slam": {"x": 21084.45, "y": -13374.82, "yaw": 4.70 },
"groundtruth": {"x": 21720.00, "y": -13480.00, "z": 1720.00, "yaw": -1.52, "pitch": 0.01, "roll": 0.00 }
},
{
"time": "6/14/2012 9:15:57 AM",
"avgcovariancedeterminant": "235377716136.071",
"ins": {"x": 21400.00, "y": -13860.00, "z": 1390.00, "yaw": 4.70, "roll": 6.28, "pitch": 0.02 },
"slam": {"x": 21070.10, "y": -13832.21, "yaw": 4.69 },
"groundtruth": {"x": 21740.00, "y": -13950.00, "z": 1720.00, "yaw": -1.53, "pitch": 0.01, "roll": 0.00 }
},
{
"time": "6/14/2012 9:15:58 AM",
"avgcovariancedeterminant": "245482264678.005",
"ins": {"x": 21390.00, "y": -14350.00, "z": 1390.00, "yaw": 4.70, "roll": 6.28, "pitch": 0.01 },
"slam": {"x": 21055.45, "y": -14321.72, "yaw": 4.69 },
"groundtruth": {"x": 21760.00, "y": -14430.00, "z": 1720.00, "yaw": -1.53, "pitch": 0.00, "roll": 0.00 }
},
{
"time": "6/14/2012 9:15:58 AM",
"avgcovariancedeterminant": "255678456203.192",
"ins": {"x": 21400.00, "y": -14790.00, "z": 1400.00, "yaw": 4.67, "roll": 6.28, "pitch": 0.03 },
"slam": {"x": 21039.13, "y": -14754.03, "yaw": 4.67 },
"groundtruth": {"x": 21770.00, "y": -14890.00, "z": 1720.00, "yaw": -1.56, "pitch": 0.01, "roll": 0.00 }
},
{
"time": "6/14/2012 9:15:59 AM",
"avgcovariancedeterminant": "261154918893.005",
"ins": {"x": 21400.00, "y": -14990.00, "z": 1390.00, "yaw": 4.68, "roll": 0.00, "pitch": 0.02 },
"slam": {"x": 21030.48, "y": -14969.18, "yaw": 4.68 },
"groundtruth": {"x": 21780.00, "y": -15130.00, "z": 1720.00, "yaw": -1.55, "pitch": 0.00, "roll": 0.00 }
},
{
"time": "6/14/2012 9:15:59 AM",
"avgcovariancedeterminant": "266713532361.498",
"ins": {"x": 21400.00, "y": -15290.00, "z": 1380.00, "yaw": 4.70, "roll": 0.00, "pitch": 0.06 },
"slam": {"x": 21018.77, "y": -15264.68, "yaw": 4.69 },
"groundtruth": {"x": 21790.00, "y": -15360.00, "z": 1710.00, "yaw": -1.53, "pitch": 0.04, "roll": 0.00 }
},
{
"time": "6/14/2012 9:15:59 AM",
"avgcovariancedeterminant": "278093867793.653",
"ins": {"x": 21410.00, "y": -15750.00, "z": 1400.00, "yaw": 4.68, "roll": 6.28, "pitch": 0.02 },
"slam": {"x": 20995.20, "y": -15719.38, "yaw": 4.68 },
"groundtruth": {"x": 21790.00, "y": -15830.00, "z": 1720.00, "yaw": -1.55, "pitch": 0.01, "roll": 0.00 }
},
{
"time": "6/14/2012 9:16:00 AM",
"avgcovariancedeterminant": "289912352585.688",
"ins": {"x": 21410.00, "y": -16200.00, "z": 1410.00, "yaw": 4.67, "roll": 6.28, "pitch": 0.02 },
"slam": {"x": 20972.91, "y": -16167.36, "yaw": 4.67 },
"groundtruth": {"x": 21800.00, "y": -16290.00, "z": 1720.00, "yaw": -1.56, "pitch": 0.00, "roll": 0.00 }
},
{
"time": "6/14/2012 9:16:01 AM",
"avgcovariancedeterminant": "301946419580.633",
"ins": {"x": 21420.00, "y": -16670.00, "z": 1420.00, "yaw": 4.68, "roll": 6.28, "pitch": 0.03 },
"slam": {"x": 20950.42, "y": -16645.45, "yaw": 4.68 },
"groundtruth": {"x": 21810.00, "y": -16760.00, "z": 1720.00, "yaw": -1.55, "pitch": 0.01, "roll": 0.00 }
},
{
"time": "6/14/2012 9:16:01 AM",
"avgcovariancedeterminant": "315344063158.415",
"ins": {"x": 21430.00, "y": -17150.00, "z": 1420.00, "yaw": 4.67, "roll": 6.28, "pitch": 0.07 },
"slam": {"x": 20924.19, "y": -17119.89, "yaw": 4.67 },
"groundtruth": {"x": 21820.00, "y": -17240.00, "z": 1710.00, "yaw": -1.56, "pitch": 0.05, "roll": 0.00 }
},
{
"time": "6/14/2012 9:16:01 AM",
"avgcovariancedeterminant": "322144711458.935",
"ins": {"x": 21460.00, "y": -17280.00, "z": 1430.00, "yaw": 4.68, "roll": 6.28, "pitch": 0.02 },
"slam": {"x": 21460.00, "y": -17280.00, "yaw": 4.68 },
"groundtruth": {"x": 21830.00, "y": -17460.00, "z": 1720.00, "yaw": -1.55, "pitch": 0.01, "roll": 0.00 }
},
{
"time": "6/14/2012 9:16:02 AM",
"avgcovariancedeterminant": "329180199899.883",
"ins": {"x": 21450.00, "y": -17600.00, "z": 1430.00, "yaw": 4.67, "roll": 6.28, "pitch": 0.02 },
"slam": {"x": 21442.45, "y": -17599.61, "yaw": 4.67 },
"groundtruth": {"x": 21830.00, "y": -17710.00, "z": 1720.00, "yaw": -1.56, "pitch": 0.01, "roll": 0.00 }
},
{
"time": "6/14/2012 9:16:03 AM",
"avgcovariancedeterminant": "343976716346.168",
"ins": {"x": 21460.00, "y": -18080.00, "z": 1390.00, "yaw": 4.68, "roll": 0.00, "pitch": 0.02 },
"slam": {"x": 21420.25, "y": -18079.06, "yaw": 4.68 },
"groundtruth": {"x": 21840.00, "y": -18180.00, "z": 1720.00, "yaw": -1.55, "pitch": 0.01, "roll": 0.00 }
},
{
"time": "6/14/2012 9:16:03 AM",
"avgcovariancedeterminant": "359241665066.607",
"ins": {"x": 21490.00, "y": -18550.00, "z": 1400.00, "yaw": 4.69, "roll": 6.28, "pitch": 0.02 },
"slam": {"x": 21398.93, "y": -18543.81, "yaw": 4.69 },
"groundtruth": {"x": 21850.00, "y": -18640.00, "z": 1720.00, "yaw": -1.54, "pitch": 0.00, "roll": 0.00 }
},
{
"time": "6/14/2012 9:16:03 AM",
"avgcovariancedeterminant": "748899766782.695",
"ins": {"x": 21490.00, "y": -19000.00, "z": 1400.00, "yaw": 4.67, "roll": 0.00, "pitch": 0.03 },
"slam": {"x": 21378.31, "y": -18993.21, "yaw": 4.67 },
"groundtruth": {"x": 21860.00, "y": -19110.00, "z": 1710.00, "yaw": -1.56, "pitch": 0.02, "roll": 0.00 }
},
{
"time": "6/14/2012 9:16:05 AM",
"avgcovariancedeterminant": "1173789681136.55",
"ins": {"x": 21480.00, "y": -19470.00, "z": 1420.00, "yaw": 4.67, "roll": 6.28, "pitch": 0.03 },
"slam": {"x": 21352.37, "y": -19459.28, "yaw": 4.67 },
"groundtruth": {"x": 21860.00, "y": -19580.00, "z": 1720.00, "yaw": -1.56, "pitch": 0.01, "roll": 0.00 }
},
{
"time": "6/14/2012 9:16:05 AM",
"avgcovariancedeterminant": "409290670838.437",
"ins": {"x": 21490.00, "y": -19930.00, "z": 1430.00, "yaw": 4.69, "roll": 6.28, "pitch": 0.02 },
"slam": {"x": 21338.55, "y": -19910.98, "yaw": 4.70 },
"groundtruth": {"x": 21880.00, "y": -20060.00, "z": 1720.00, "yaw": -1.53, "pitch": 0.00, "roll": 0.00 }
},
{
"time": "6/14/2012 9:16:05 AM",
"avgcovariancedeterminant": "417564070044.531",
"ins": {"x": 21490.00, "y": -20080.00, "z": 1430.00, "yaw": 4.68, "roll": 6.28, "pitch": 0.03 },
"slam": {"x": 21329.81, "y": -20129.22, "yaw": 4.68 },
"groundtruth": {"x": 21880.00, "y": -20280.00, "z": 1710.00, "yaw": -1.55, "pitch": 0.04, "roll": 0.00 }
},
{
"time": "6/14/2012 9:16:05 AM",
"avgcovariancedeterminant": "427280069611.561",
"ins": {"x": 21500.00, "y": -20400.00, "z": 1450.00, "yaw": 4.69, "roll": 6.28, "pitch": 0.02 },
"slam": {"x": 21321.23, "y": -20369.82, "yaw": 4.69 },
"groundtruth": {"x": 21890.00, "y": -20520.00, "z": 1720.00, "yaw": -1.54, "pitch": 0.00, "roll": 0.00 }
},
{
"time": "6/14/2012 9:16:05 AM",
"avgcovariancedeterminant": "436395636054.319",
"ins": {"x": 21500.00, "y": -20550.00, "z": 1460.00, "yaw": 4.68, "roll": 0.00, "pitch": 0.01 },
"slam": {"x": 21314.45, "y": -20597.07, "yaw": 4.69 },
"groundtruth": {"x": 21900.00, "y": -20740.00, "z": 1720.00, "yaw": -1.54, "pitch": 0.01, "roll": 0.00 }
},
{
"time": "6/14/2012 9:16:07 AM",
"avgcovariancedeterminant": "466544660867.533",
"ins": {"x": 21520.00, "y": -21340.00, "z": 1460.00, "yaw": 4.69, "roll": 6.28, "pitch": 0.03 },
"slam": {"x": 21287.08, "y": -21307.97, "yaw": 4.69 },
"groundtruth": {"x": 21920.00, "y": -21460.00, "z": 1710.00, "yaw": -1.54, "pitch": 0.02, "roll": 0.00 }
},
{
"time": "6/14/2012 9:16:08 AM",
"avgcovariancedeterminant": "480686954479.118",
"ins": {"x": 21550.00, "y": -21640.00, "z": 1480.00, "yaw": 4.69, "roll": 6.28, "pitch": 0.01 },
"slam": {"x": 21277.68, "y": -21632.36, "yaw": 4.70 },
"groundtruth": {"x": 21930.00, "y": -21780.00, "z": 1720.00, "yaw": -1.53, "pitch": 0.00, "roll": 0.00 }
},
{
"time": "6/14/2012 9:16:36 AM",
"avgcovariancedeterminant": "449841721942.61",
"ins": {"x": 21530.00, "y": -21000.00, "z": 1490.00, "yaw": 4.70, "roll": 6.28, "pitch": 6.28 },
"slam": {"x": 21297.50, "y": -20927.95, "yaw": 4.71 },
"groundtruth": {"x": 21900.00, "y": -21070.00, "z": 1720.00, "yaw": -1.52, "pitch": 0.00, "roll": 0.00 }
},
{
"time": "6/14/2012 9:16:37 AM",
"avgcovariancedeterminant": "420418230381.782",
"ins": {"x": 21480.00, "y": -20220.00, "z": 1520.00, "yaw": 4.72, "roll": 6.28, "pitch": 0.01 },
"slam": {"x": 21304.09, "y": -20223.28, "yaw": 4.73 },
"groundtruth": {"x": 21870.00, "y": -20370.00, "z": 1720.00, "yaw": -1.50, "pitch": 0.00, "roll": 0.00 }
},
{
"time": "6/14/2012 9:16:38 AM",
"avgcovariancedeterminant": "401632082621.977",
"ins": {"x": 21460.00, "y": -19730.00, "z": 1540.00, "yaw": 4.70, "roll": 6.28, "pitch": 0.01 },
"slam": {"x": 21319.54, "y": -19735.39, "yaw": 4.70 },
"groundtruth": {"x": 21850.00, "y": -19880.00, "z": 1720.00, "yaw": -1.53, "pitch": 0.00, "roll": 0.00 }
},
